languageformsapplication/Data.db
languageformsapplication/SpeakerForm.py
languageformsapplication/__init__.py
languageformsapplication/icon.ico
languageformsapplication/nltk_data/corpora/brown/CONTENTS
languageformsapplication/nltk_data/corpora/brown/README
languageformsapplication/nltk_data/corpora/brown/ca01
languageformsapplication/nltk_data/corpora/brown/ca02
languageformsapplication/nltk_data/corpora/brown/ca03
languageformsapplication/nltk_data/corpora/brown/ca04
languageformsapplication/nltk_data/corpora/brown/ca05
languageformsapplication/nltk_data/corpora/brown/ca06
languageformsapplication/nltk_data/corpora/brown/ca07
languageformsapplication/nltk_data/corpora/brown/ca08
languageformsapplication/nltk_data/corpora/brown/ca09
languageformsapplication/nltk_data/corpora/brown/ca10
languageformsapplication/nltk_data/corpora/brown/ca11
languageformsapplication/nltk_data/corpora/brown/ca12
languageformsapplication/nltk_data/corpora/brown/ca13
languageformsapplication/nltk_data/corpora/brown/ca14
languageformsapplication/nltk_data/corpora/brown/ca15
languageformsapplication/nltk_data/corpora/brown/ca16
languageformsapplication/nltk_data/corpora/brown/ca17
languageformsapplication/nltk_data/corpora/brown/ca18
languageformsapplication/nltk_data/corpora/brown/ca19
languageformsapplication/nltk_data/corpora/brown/ca20
languageformsapplication/nltk_data/corpora/brown/ca21
languageformsapplication/nltk_data/corpora/brown/ca22
languageformsapplication/nltk_data/corpora/brown/ca23
languageformsapplication/nltk_data/corpora/brown/ca24
languageformsapplication/nltk_data/corpora/brown/ca25
languageformsapplication/nltk_data/corpora/brown/ca26
languageformsapplication/nltk_data/corpora/brown/ca27
languageformsapplication/nltk_data/corpora/brown/ca28
languageformsapplication/nltk_data/corpora/brown/ca29
languageformsapplication/nltk_data/corpora/brown/ca30
languageformsapplication/nltk_data/corpora/brown/ca31
languageformsapplication/nltk_data/corpora/brown/ca32
languageformsapplication-1.0.1.dist-info/METADATA
languageformsapplication-1.0.1.dist-info/WHEEL
languageformsapplication-1.0.1.dist-info/licenses/LICENSE.txt
languageformsapplication-1.0.1.dist-info/RECORD
