Metadata-Version: 2.1
Name: languageformsapplication
Version: 1.0.1
Summary: To help improve learning a language
Project-URL: Homepage, https://github.com/yasharsajadi/languageformsapplication
Author-email: "Seyed Mousa Sajadi(WinCento)" <sajadimousa@gmail.com>
License-File: LICENSE.txt
Classifier: License :: OSI Approved :: MIT License
Classifier: Operating System :: OS Independent
Classifier: Programming Language :: Python :: 3
Requires-Python: >=3.7
